{
  "type": "GROUP",
"name": "Global Information",
"path": "",
"pathFormatted": "group_missing-name-b06d1",
"stats": {
    "name": "Global Information",
    "numberOfRequests": {
        "total": 35,
        "ok": 35,
        "ko": 0
    },
    "minResponseTime": {
        "total": 19,
        "ok": 19,
        "ko": 0
    },
    "maxResponseTime": {
        "total": 679,
        "ok": 679,
        "ko": 0
    },
    "meanResponseTime": {
        "total": 271,
        "ok": 271,
        "ko": 0
    },
    "standardDeviation": {
        "total": 173,
        "ok": 173,
        "ko": 0
    },
    "percentiles1": {
        "total": 305,
        "ok": 305,
        "ko": 0
    },
    "percentiles2": {
        "total": 381,
        "ok": 381,
        "ko": 0
    },
    "percentiles3": {
        "total": 540,
        "ok": 540,
        "ko": 0
    },
    "percentiles4": {
        "total": 639,
        "ok": 639,
        "ko": 0
    },
    "group1": {
        "name": "t < 800 ms",
        "count": 35,
        "percentage": 100
    },
    "group2": {
        "name": "800 ms < t < 1200 ms",
        "count": 0,
        "percentage": 0
    },
    "group3": {
        "name": "t > 1200 ms",
        "count": 0,
        "percentage": 0
    },
    "group4": {
        "name": "failed",
        "count": 0,
        "percentage": 0
    },
    "meanNumberOfRequestsPerSecond": {
        "total": 0.5147058823529411,
        "ok": 0.5147058823529411,
        "ko": 0
    }
},
"contents": {
"req_trigger-login-8dec8": {
        "type": "REQUEST",
        "name": "Trigger login",
"path": "Trigger login",
"pathFormatted": "req_trigger-login-8dec8",
"stats": {
    "name": "Trigger login",
    "numberOfRequests": {
        "total": 1,
        "ok": 1,
        "ko": 0
    },
    "minResponseTime": {
        "total": 124,
        "ok": 124,
        "ko": 0
    },
    "maxResponseTime": {
        "total": 124,
        "ok": 124,
        "ko": 0
    },
    "meanResponseTime": {
        "total": 124,
        "ok": 124,
        "ko": 0
    },
    "standardDeviation": {
        "total": 0,
        "ok": 0,
        "ko": 0
    },
    "percentiles1": {
        "total": 124,
        "ok": 124,
        "ko": 0
    },
    "percentiles2": {
        "total": 124,
        "ok": 124,
        "ko": 0
    },
    "percentiles3": {
        "total": 124,
        "ok": 124,
        "ko": 0
    },
    "percentiles4": {
        "total": 124,
        "ok": 124,
        "ko": 0
    },
    "group1": {
        "name": "t < 800 ms",
        "count": 1,
        "percentage": 100
    },
    "group2": {
        "name": "800 ms < t < 1200 ms",
        "count": 0,
        "percentage": 0
    },
    "group3": {
        "name": "t > 1200 ms",
        "count": 0,
        "percentage": 0
    },
    "group4": {
        "name": "failed",
        "count": 0,
        "percentage": 0
    },
    "meanNumberOfRequestsPerSecond": {
        "total": 0.014705882352941176,
        "ok": 0.014705882352941176,
        "ko": 0
    }
}
    },"req_trigger-login-r-6c3d2": {
        "type": "REQUEST",
        "name": "Trigger login Redirect 1",
"path": "Trigger login Redirect 1",
"pathFormatted": "req_trigger-login-r-6c3d2",
"stats": {
    "name": "Trigger login Redirect 1",
    "numberOfRequests": {
        "total": 1,
        "ok": 1,
        "ko": 0
    },
    "minResponseTime": {
        "total": 19,
        "ok": 19,
        "ko": 0
    },
    "maxResponseTime": {
        "total": 19,
        "ok": 19,
        "ko": 0
    },
    "meanResponseTime": {
        "total": 19,
        "ok": 19,
        "ko": 0
    },
    "standardDeviation": {
        "total": 0,
        "ok": 0,
        "ko": 0
    },
    "percentiles1": {
        "total": 19,
        "ok": 19,
        "ko": 0
    },
    "percentiles2": {
        "total": 19,
        "ok": 19,
        "ko": 0
    },
    "percentiles3": {
        "total": 19,
        "ok": 19,
        "ko": 0
    },
    "percentiles4": {
        "total": 19,
        "ok": 19,
        "ko": 0
    },
    "group1": {
        "name": "t < 800 ms",
        "count": 1,
        "percentage": 100
    },
    "group2": {
        "name": "800 ms < t < 1200 ms",
        "count": 0,
        "percentage": 0
    },
    "group3": {
        "name": "t > 1200 ms",
        "count": 0,
        "percentage": 0
    },
    "group4": {
        "name": "failed",
        "count": 0,
        "percentage": 0
    },
    "meanNumberOfRequestsPerSecond": {
        "total": 0.014705882352941176,
        "ok": 0.014705882352941176,
        "ko": 0
    }
}
    },"req_trigger-login-r-8d6c2": {
        "type": "REQUEST",
        "name": "Trigger login Redirect 2",
"path": "Trigger login Redirect 2",
"pathFormatted": "req_trigger-login-r-8d6c2",
"stats": {
    "name": "Trigger login Redirect 2",
    "numberOfRequests": {
        "total": 1,
        "ok": 1,
        "ko": 0
    },
    "minResponseTime": {
        "total": 242,
        "ok": 242,
        "ko": 0
    },
    "maxResponseTime": {
        "total": 242,
        "ok": 242,
        "ko": 0
    },
    "meanResponseTime": {
        "total": 242,
        "ok": 242,
        "ko": 0
    },
    "standardDeviation": {
        "total": 0,
        "ok": 0,
        "ko": 0
    },
    "percentiles1": {
        "total": 242,
        "ok": 242,
        "ko": 0
    },
    "percentiles2": {
        "total": 242,
        "ok": 242,
        "ko": 0
    },
    "percentiles3": {
        "total": 242,
        "ok": 242,
        "ko": 0
    },
    "percentiles4": {
        "total": 242,
        "ok": 242,
        "ko": 0
    },
    "group1": {
        "name": "t < 800 ms",
        "count": 1,
        "percentage": 100
    },
    "group2": {
        "name": "800 ms < t < 1200 ms",
        "count": 0,
        "percentage": 0
    },
    "group3": {
        "name": "t > 1200 ms",
        "count": 0,
        "percentage": 0
    },
    "group4": {
        "name": "failed",
        "count": 0,
        "percentage": 0
    },
    "meanNumberOfRequestsPerSecond": {
        "total": 0.014705882352941176,
        "ok": 0.014705882352941176,
        "ko": 0
    }
}
    },"req_login---submit-9bf36": {
        "type": "REQUEST",
        "name": "Login - submit",
"path": "Login - submit",
"pathFormatted": "req_login---submit-9bf36",
"stats": {
    "name": "Login - submit",
    "numberOfRequests": {
        "total": 1,
        "ok": 1,
        "ko": 0
    },
    "minResponseTime": {
        "total": 531,
        "ok": 531,
        "ko": 0
    },
    "maxResponseTime": {
        "total": 531,
        "ok": 531,
        "ko": 0
    },
    "meanResponseTime": {
        "total": 531,
        "ok": 531,
        "ko": 0
    },
    "standardDeviation": {
        "total": 0,
        "ok": 0,
        "ko": 0
    },
    "percentiles1": {
        "total": 531,
        "ok": 531,
        "ko": 0
    },
    "percentiles2": {
        "total": 531,
        "ok": 531,
        "ko": 0
    },
    "percentiles3": {
        "total": 531,
        "ok": 531,
        "ko": 0
    },
    "percentiles4": {
        "total": 531,
        "ok": 531,
        "ko": 0
    },
    "group1": {
        "name": "t < 800 ms",
        "count": 1,
        "percentage": 100
    },
    "group2": {
        "name": "800 ms < t < 1200 ms",
        "count": 0,
        "percentage": 0
    },
    "group3": {
        "name": "t > 1200 ms",
        "count": 0,
        "percentage": 0
    },
    "group4": {
        "name": "failed",
        "count": 0,
        "percentage": 0
    },
    "meanNumberOfRequestsPerSecond": {
        "total": 0.014705882352941176,
        "ok": 0.014705882352941176,
        "ko": 0
    }
}
    },"req_login---submit--0f7e7": {
        "type": "REQUEST",
        "name": "Login - submit Redirect 1",
"path": "Login - submit Redirect 1",
"pathFormatted": "req_login---submit--0f7e7",
"stats": {
    "name": "Login - submit Redirect 1",
    "numberOfRequests": {
        "total": 1,
        "ok": 1,
        "ko": 0
    },
    "minResponseTime": {
        "total": 407,
        "ok": 407,
        "ko": 0
    },
    "maxResponseTime": {
        "total": 407,
        "ok": 407,
        "ko": 0
    },
    "meanResponseTime": {
        "total": 407,
        "ok": 407,
        "ko": 0
    },
    "standardDeviation": {
        "total": 0,
        "ok": 0,
        "ko": 0
    },
    "percentiles1": {
        "total": 407,
        "ok": 407,
        "ko": 0
    },
    "percentiles2": {
        "total": 407,
        "ok": 407,
        "ko": 0
    },
    "percentiles3": {
        "total": 407,
        "ok": 407,
        "ko": 0
    },
    "percentiles4": {
        "total": 407,
        "ok": 407,
        "ko": 0
    },
    "group1": {
        "name": "t < 800 ms",
        "count": 1,
        "percentage": 100
    },
    "group2": {
        "name": "800 ms < t < 1200 ms",
        "count": 0,
        "percentage": 0
    },
    "group3": {
        "name": "t > 1200 ms",
        "count": 0,
        "percentage": 0
    },
    "group4": {
        "name": "failed",
        "count": 0,
        "percentage": 0
    },
    "meanNumberOfRequestsPerSecond": {
        "total": 0.014705882352941176,
        "ok": 0.014705882352941176,
        "ko": 0
    }
}
    },"req_login---submit--67015": {
        "type": "REQUEST",
        "name": "Login - submit Redirect 2",
"path": "Login - submit Redirect 2",
"pathFormatted": "req_login---submit--67015",
"stats": {
    "name": "Login - submit Redirect 2",
    "numberOfRequests": {
        "total": 1,
        "ok": 1,
        "ko": 0
    },
    "minResponseTime": {
        "total": 522,
        "ok": 522,
        "ko": 0
    },
    "maxResponseTime": {
        "total": 522,
        "ok": 522,
        "ko": 0
    },
    "meanResponseTime": {
        "total": 522,
        "ok": 522,
        "ko": 0
    },
    "standardDeviation": {
        "total": 0,
        "ok": 0,
        "ko": 0
    },
    "percentiles1": {
        "total": 522,
        "ok": 522,
        "ko": 0
    },
    "percentiles2": {
        "total": 522,
        "ok": 522,
        "ko": 0
    },
    "percentiles3": {
        "total": 522,
        "ok": 522,
        "ko": 0
    },
    "percentiles4": {
        "total": 522,
        "ok": 522,
        "ko": 0
    },
    "group1": {
        "name": "t < 800 ms",
        "count": 1,
        "percentage": 100
    },
    "group2": {
        "name": "800 ms < t < 1200 ms",
        "count": 0,
        "percentage": 0
    },
    "group3": {
        "name": "t > 1200 ms",
        "count": 0,
        "percentage": 0
    },
    "group4": {
        "name": "failed",
        "count": 0,
        "percentage": 0
    },
    "meanNumberOfRequestsPerSecond": {
        "total": 0.014705882352941176,
        "ok": 0.014705882352941176,
        "ko": 0
    }
}
    },"req_make-a-new-mone-7d4a5": {
        "type": "REQUEST",
        "name": "Make a new money claim",
"path": "Make a new money claim",
"pathFormatted": "req_make-a-new-mone-7d4a5",
"stats": {
    "name": "Make a new money claim",
    "numberOfRequests": {
        "total": 1,
        "ok": 1,
        "ko": 0
    },
    "minResponseTime": {
        "total": 165,
        "ok": 165,
        "ko": 0
    },
    "maxResponseTime": {
        "total": 165,
        "ok": 165,
        "ko": 0
    },
    "meanResponseTime": {
        "total": 165,
        "ok": 165,
        "ko": 0
    },
    "standardDeviation": {
        "total": 0,
        "ok": 0,
        "ko": 0
    },
    "percentiles1": {
        "total": 165,
        "ok": 165,
        "ko": 0
    },
    "percentiles2": {
        "total": 165,
        "ok": 165,
        "ko": 0
    },
    "percentiles3": {
        "total": 165,
        "ok": 165,
        "ko": 0
    },
    "percentiles4": {
        "total": 165,
        "ok": 165,
        "ko": 0
    },
    "group1": {
        "name": "t < 800 ms",
        "count": 1,
        "percentage": 100
    },
    "group2": {
        "name": "800 ms < t < 1200 ms",
        "count": 0,
        "percentage": 0
    },
    "group3": {
        "name": "t > 1200 ms",
        "count": 0,
        "percentage": 0
    },
    "group4": {
        "name": "failed",
        "count": 0,
        "percentage": 0
    },
    "meanNumberOfRequestsPerSecond": {
        "total": 0.014705882352941176,
        "ok": 0.014705882352941176,
        "ko": 0
    }
}
    },"req_eligibility-sta-e85be": {
        "type": "REQUEST",
        "name": "Eligibility start",
"path": "Eligibility start",
"pathFormatted": "req_eligibility-sta-e85be",
"stats": {
    "name": "Eligibility start",
    "numberOfRequests": {
        "total": 1,
        "ok": 1,
        "ko": 0
    },
    "minResponseTime": {
        "total": 98,
        "ok": 98,
        "ko": 0
    },
    "maxResponseTime": {
        "total": 98,
        "ok": 98,
        "ko": 0
    },
    "meanResponseTime": {
        "total": 98,
        "ok": 98,
        "ko": 0
    },
    "standardDeviation": {
        "total": 0,
        "ok": 0,
        "ko": 0
    },
    "percentiles1": {
        "total": 98,
        "ok": 98,
        "ko": 0
    },
    "percentiles2": {
        "total": 98,
        "ok": 98,
        "ko": 0
    },
    "percentiles3": {
        "total": 98,
        "ok": 98,
        "ko": 0
    },
    "percentiles4": {
        "total": 98,
        "ok": 98,
        "ko": 0
    },
    "group1": {
        "name": "t < 800 ms",
        "count": 1,
        "percentage": 100
    },
    "group2": {
        "name": "800 ms < t < 1200 ms",
        "count": 0,
        "percentage": 0
    },
    "group3": {
        "name": "t > 1200 ms",
        "count": 0,
        "percentage": 0
    },
    "group4": {
        "name": "failed",
        "count": 0,
        "percentage": 0
    },
    "meanNumberOfRequestsPerSecond": {
        "total": 0.014705882352941176,
        "ok": 0.014705882352941176,
        "ko": 0
    }
}
    },"req_find-out-if-you-0a396": {
        "type": "REQUEST",
        "name": "Find out if you can use this service",
"path": "Find out if you can use this service",
"pathFormatted": "req_find-out-if-you-0a396",
"stats": {
    "name": "Find out if you can use this service",
    "numberOfRequests": {
        "total": 1,
        "ok": 1,
        "ko": 0
    },
    "minResponseTime": {
        "total": 322,
        "ok": 322,
        "ko": 0
    },
    "maxResponseTime": {
        "total": 322,
        "ok": 322,
        "ko": 0
    },
    "meanResponseTime": {
        "total": 322,
        "ok": 322,
        "ko": 0
    },
    "standardDeviation": {
        "total": 0,
        "ok": 0,
        "ko": 0
    },
    "percentiles1": {
        "total": 322,
        "ok": 322,
        "ko": 0
    },
    "percentiles2": {
        "total": 322,
        "ok": 322,
        "ko": 0
    },
    "percentiles3": {
        "total": 322,
        "ok": 322,
        "ko": 0
    },
    "percentiles4": {
        "total": 322,
        "ok": 322,
        "ko": 0
    },
    "group1": {
        "name": "t < 800 ms",
        "count": 1,
        "percentage": 100
    },
    "group2": {
        "name": "800 ms < t < 1200 ms",
        "count": 0,
        "percentage": 0
    },
    "group3": {
        "name": "t > 1200 ms",
        "count": 0,
        "percentage": 0
    },
    "group4": {
        "name": "failed",
        "count": 0,
        "percentage": 0
    },
    "meanNumberOfRequestsPerSecond": {
        "total": 0.014705882352941176,
        "ok": 0.014705882352941176,
        "ko": 0
    }
}
    },"req_eligibility---t-968e6": {
        "type": "REQUEST",
        "name": "Eligibility - Total amount you’re claiming",
"path": "Eligibility - Total amount you’re claiming",
"pathFormatted": "req_eligibility---t-968e6",
"stats": {
    "name": "Eligibility - Total amount you’re claiming",
    "numberOfRequests": {
        "total": 1,
        "ok": 1,
        "ko": 0
    },
    "minResponseTime": {
        "total": 71,
        "ok": 71,
        "ko": 0
    },
    "maxResponseTime": {
        "total": 71,
        "ok": 71,
        "ko": 0
    },
    "meanResponseTime": {
        "total": 71,
        "ok": 71,
        "ko": 0
    },
    "standardDeviation": {
        "total": 0,
        "ok": 0,
        "ko": 0
    },
    "percentiles1": {
        "total": 71,
        "ok": 71,
        "ko": 0
    },
    "percentiles2": {
        "total": 71,
        "ok": 71,
        "ko": 0
    },
    "percentiles3": {
        "total": 71,
        "ok": 71,
        "ko": 0
    },
    "percentiles4": {
        "total": 71,
        "ok": 71,
        "ko": 0
    },
    "group1": {
        "name": "t < 800 ms",
        "count": 1,
        "percentage": 100
    },
    "group2": {
        "name": "800 ms < t < 1200 ms",
        "count": 0,
        "percentage": 0
    },
    "group3": {
        "name": "t > 1200 ms",
        "count": 0,
        "percentage": 0
    },
    "group4": {
        "name": "failed",
        "count": 0,
        "percentage": 0
    },
    "meanNumberOfRequestsPerSecond": {
        "total": 0.014705882352941176,
        "ok": 0.014705882352941176,
        "ko": 0
    }
}
    },"req_eligibility---h-86c44": {
        "type": "REQUEST",
        "name": "Eligibility - help with fees POST",
"path": "Eligibility - help with fees POST",
"pathFormatted": "req_eligibility---h-86c44",
"stats": {
    "name": "Eligibility - help with fees POST",
    "numberOfRequests": {
        "total": 1,
        "ok": 1,
        "ko": 0
    },
    "minResponseTime": {
        "total": 59,
        "ok": 59,
        "ko": 0
    },
    "maxResponseTime": {
        "total": 59,
        "ok": 59,
        "ko": 0
    },
    "meanResponseTime": {
        "total": 59,
        "ok": 59,
        "ko": 0
    },
    "standardDeviation": {
        "total": 0,
        "ok": 0,
        "ko": 0
    },
    "percentiles1": {
        "total": 59,
        "ok": 59,
        "ko": 0
    },
    "percentiles2": {
        "total": 59,
        "ok": 59,
        "ko": 0
    },
    "percentiles3": {
        "total": 59,
        "ok": 59,
        "ko": 0
    },
    "percentiles4": {
        "total": 59,
        "ok": 59,
        "ko": 0
    },
    "group1": {
        "name": "t < 800 ms",
        "count": 1,
        "percentage": 100
    },
    "group2": {
        "name": "800 ms < t < 1200 ms",
        "count": 0,
        "percentage": 0
    },
    "group3": {
        "name": "t > 1200 ms",
        "count": 0,
        "percentage": 0
    },
    "group4": {
        "name": "failed",
        "count": 0,
        "percentage": 0
    },
    "meanNumberOfRequestsPerSecond": {
        "total": 0.014705882352941176,
        "ok": 0.014705882352941176,
        "ko": 0
    }
}
    },"req_eligibility---c-e851b": {
        "type": "REQUEST",
        "name": "Eligibility - claimant address POST",
"path": "Eligibility - claimant address POST",
"pathFormatted": "req_eligibility---c-e851b",
"stats": {
    "name": "Eligibility - claimant address POST",
    "numberOfRequests": {
        "total": 1,
        "ok": 1,
        "ko": 0
    },
    "minResponseTime": {
        "total": 91,
        "ok": 91,
        "ko": 0
    },
    "maxResponseTime": {
        "total": 91,
        "ok": 91,
        "ko": 0
    },
    "meanResponseTime": {
        "total": 91,
        "ok": 91,
        "ko": 0
    },
    "standardDeviation": {
        "total": 0,
        "ok": 0,
        "ko": 0
    },
    "percentiles1": {
        "total": 91,
        "ok": 91,
        "ko": 0
    },
    "percentiles2": {
        "total": 91,
        "ok": 91,
        "ko": 0
    },
    "percentiles3": {
        "total": 91,
        "ok": 91,
        "ko": 0
    },
    "percentiles4": {
        "total": 91,
        "ok": 91,
        "ko": 0
    },
    "group1": {
        "name": "t < 800 ms",
        "count": 1,
        "percentage": 100
    },
    "group2": {
        "name": "800 ms < t < 1200 ms",
        "count": 0,
        "percentage": 0
    },
    "group3": {
        "name": "t > 1200 ms",
        "count": 0,
        "percentage": 0
    },
    "group4": {
        "name": "failed",
        "count": 0,
        "percentage": 0
    },
    "meanNumberOfRequestsPerSecond": {
        "total": 0.014705882352941176,
        "ok": 0.014705882352941176,
        "ko": 0
    }
}
    },"req_eligibility---d-cabe5": {
        "type": "REQUEST",
        "name": "Eligibility - defendant address POST",
"path": "Eligibility - defendant address POST",
"pathFormatted": "req_eligibility---d-cabe5",
"stats": {
    "name": "Eligibility - defendant address POST",
    "numberOfRequests": {
        "total": 1,
        "ok": 1,
        "ko": 0
    },
    "minResponseTime": {
        "total": 72,
        "ok": 72,
        "ko": 0
    },
    "maxResponseTime": {
        "total": 72,
        "ok": 72,
        "ko": 0
    },
    "meanResponseTime": {
        "total": 72,
        "ok": 72,
        "ko": 0
    },
    "standardDeviation": {
        "total": 0,
        "ok": 0,
        "ko": 0
    },
    "percentiles1": {
        "total": 72,
        "ok": 72,
        "ko": 0
    },
    "percentiles2": {
        "total": 72,
        "ok": 72,
        "ko": 0
    },
    "percentiles3": {
        "total": 72,
        "ok": 72,
        "ko": 0
    },
    "percentiles4": {
        "total": 72,
        "ok": 72,
        "ko": 0
    },
    "group1": {
        "name": "t < 800 ms",
        "count": 1,
        "percentage": 100
    },
    "group2": {
        "name": "800 ms < t < 1200 ms",
        "count": 0,
        "percentage": 0
    },
    "group3": {
        "name": "t > 1200 ms",
        "count": 0,
        "percentage": 0
    },
    "group4": {
        "name": "failed",
        "count": 0,
        "percentage": 0
    },
    "meanNumberOfRequestsPerSecond": {
        "total": 0.014705882352941176,
        "ok": 0.014705882352941176,
        "ko": 0
    }
}
    },"req_eligibility---o-00835": {
        "type": "REQUEST",
        "name": "Eligibility - over 18 POST",
"path": "Eligibility - over 18 POST",
"pathFormatted": "req_eligibility---o-00835",
"stats": {
    "name": "Eligibility - over 18 POST",
    "numberOfRequests": {
        "total": 1,
        "ok": 1,
        "ko": 0
    },
    "minResponseTime": {
        "total": 61,
        "ok": 61,
        "ko": 0
    },
    "maxResponseTime": {
        "total": 61,
        "ok": 61,
        "ko": 0
    },
    "meanResponseTime": {
        "total": 61,
        "ok": 61,
        "ko": 0
    },
    "standardDeviation": {
        "total": 0,
        "ok": 0,
        "ko": 0
    },
    "percentiles1": {
        "total": 61,
        "ok": 61,
        "ko": 0
    },
    "percentiles2": {
        "total": 61,
        "ok": 61,
        "ko": 0
    },
    "percentiles3": {
        "total": 61,
        "ok": 61,
        "ko": 0
    },
    "percentiles4": {
        "total": 61,
        "ok": 61,
        "ko": 0
    },
    "group1": {
        "name": "t < 800 ms",
        "count": 1,
        "percentage": 100
    },
    "group2": {
        "name": "800 ms < t < 1200 ms",
        "count": 0,
        "percentage": 0
    },
    "group3": {
        "name": "t > 1200 ms",
        "count": 0,
        "percentage": 0
    },
    "group4": {
        "name": "failed",
        "count": 0,
        "percentage": 0
    },
    "meanNumberOfRequestsPerSecond": {
        "total": 0.014705882352941176,
        "ok": 0.014705882352941176,
        "ko": 0
    }
}
    },"req_eligibility---p-169e1": {
        "type": "REQUEST",
        "name": "Eligibility - PERSONAL_CLAIM claimant POST",
"path": "Eligibility - PERSONAL_CLAIM claimant POST",
"pathFormatted": "req_eligibility---p-169e1",
"stats": {
    "name": "Eligibility - PERSONAL_CLAIM claimant POST",
    "numberOfRequests": {
        "total": 1,
        "ok": 1,
        "ko": 0
    },
    "minResponseTime": {
        "total": 87,
        "ok": 87,
        "ko": 0
    },
    "maxResponseTime": {
        "total": 87,
        "ok": 87,
        "ko": 0
    },
    "meanResponseTime": {
        "total": 87,
        "ok": 87,
        "ko": 0
    },
    "standardDeviation": {
        "total": 0,
        "ok": 0,
        "ko": 0
    },
    "percentiles1": {
        "total": 87,
        "ok": 87,
        "ko": 0
    },
    "percentiles2": {
        "total": 87,
        "ok": 87,
        "ko": 0
    },
    "percentiles3": {
        "total": 87,
        "ok": 87,
        "ko": 0
    },
    "percentiles4": {
        "total": 87,
        "ok": 87,
        "ko": 0
    },
    "group1": {
        "name": "t < 800 ms",
        "count": 1,
        "percentage": 100
    },
    "group2": {
        "name": "800 ms < t < 1200 ms",
        "count": 0,
        "percentage": 0
    },
    "group3": {
        "name": "t > 1200 ms",
        "count": 0,
        "percentage": 0
    },
    "group4": {
        "name": "failed",
        "count": 0,
        "percentage": 0
    },
    "meanNumberOfRequestsPerSecond": {
        "total": 0.014705882352941176,
        "ok": 0.014705882352941176,
        "ko": 0
    }
}
    },"req_eligibility---s-0f48d": {
        "type": "REQUEST",
        "name": "Eligibility - single defendant POST",
"path": "Eligibility - single defendant POST",
"pathFormatted": "req_eligibility---s-0f48d",
"stats": {
    "name": "Eligibility - single defendant POST",
    "numberOfRequests": {
        "total": 1,
        "ok": 1,
        "ko": 0
    },
    "minResponseTime": {
        "total": 84,
        "ok": 84,
        "ko": 0
    },
    "maxResponseTime": {
        "total": 84,
        "ok": 84,
        "ko": 0
    },
    "meanResponseTime": {
        "total": 84,
        "ok": 84,
        "ko": 0
    },
    "standardDeviation": {
        "total": 0,
        "ok": 0,
        "ko": 0
    },
    "percentiles1": {
        "total": 84,
        "ok": 84,
        "ko": 0
    },
    "percentiles2": {
        "total": 84,
        "ok": 84,
        "ko": 0
    },
    "percentiles3": {
        "total": 84,
        "ok": 84,
        "ko": 0
    },
    "percentiles4": {
        "total": 84,
        "ok": 84,
        "ko": 0
    },
    "group1": {
        "name": "t < 800 ms",
        "count": 1,
        "percentage": 100
    },
    "group2": {
        "name": "800 ms < t < 1200 ms",
        "count": 0,
        "percentage": 0
    },
    "group3": {
        "name": "t > 1200 ms",
        "count": 0,
        "percentage": 0
    },
    "group4": {
        "name": "failed",
        "count": 0,
        "percentage": 0
    },
    "meanNumberOfRequestsPerSecond": {
        "total": 0.014705882352941176,
        "ok": 0.014705882352941176,
        "ko": 0
    }
}
    },"req_eligibility---g-c1ac3": {
        "type": "REQUEST",
        "name": "Eligibility - government department POST",
"path": "Eligibility - government department POST",
"pathFormatted": "req_eligibility---g-c1ac3",
"stats": {
    "name": "Eligibility - government department POST",
    "numberOfRequests": {
        "total": 1,
        "ok": 1,
        "ko": 0
    },
    "minResponseTime": {
        "total": 57,
        "ok": 57,
        "ko": 0
    },
    "maxResponseTime": {
        "total": 57,
        "ok": 57,
        "ko": 0
    },
    "meanResponseTime": {
        "total": 57,
        "ok": 57,
        "ko": 0
    },
    "standardDeviation": {
        "total": 0,
        "ok": 0,
        "ko": 0
    },
    "percentiles1": {
        "total": 57,
        "ok": 57,
        "ko": 0
    },
    "percentiles2": {
        "total": 57,
        "ok": 57,
        "ko": 0
    },
    "percentiles3": {
        "total": 57,
        "ok": 57,
        "ko": 0
    },
    "percentiles4": {
        "total": 57,
        "ok": 57,
        "ko": 0
    },
    "group1": {
        "name": "t < 800 ms",
        "count": 1,
        "percentage": 100
    },
    "group2": {
        "name": "800 ms < t < 1200 ms",
        "count": 0,
        "percentage": 0
    },
    "group3": {
        "name": "t > 1200 ms",
        "count": 0,
        "percentage": 0
    },
    "group4": {
        "name": "failed",
        "count": 0,
        "percentage": 0
    },
    "meanNumberOfRequestsPerSecond": {
        "total": 0.014705882352941176,
        "ok": 0.014705882352941176,
        "ko": 0
    }
}
    },"req_eligibility---t-8c74e": {
        "type": "REQUEST",
        "name": "Eligibility - tenancy deposit POST",
"path": "Eligibility - tenancy deposit POST",
"pathFormatted": "req_eligibility---t-8c74e",
"stats": {
    "name": "Eligibility - tenancy deposit POST",
    "numberOfRequests": {
        "total": 1,
        "ok": 1,
        "ko": 0
    },
    "minResponseTime": {
        "total": 65,
        "ok": 65,
        "ko": 0
    },
    "maxResponseTime": {
        "total": 65,
        "ok": 65,
        "ko": 0
    },
    "meanResponseTime": {
        "total": 65,
        "ok": 65,
        "ko": 0
    },
    "standardDeviation": {
        "total": 0,
        "ok": 0,
        "ko": 0
    },
    "percentiles1": {
        "total": 65,
        "ok": 65,
        "ko": 0
    },
    "percentiles2": {
        "total": 65,
        "ok": 65,
        "ko": 0
    },
    "percentiles3": {
        "total": 65,
        "ok": 65,
        "ko": 0
    },
    "percentiles4": {
        "total": 65,
        "ok": 65,
        "ko": 0
    },
    "group1": {
        "name": "t < 800 ms",
        "count": 1,
        "percentage": 100
    },
    "group2": {
        "name": "800 ms < t < 1200 ms",
        "count": 0,
        "percentage": 0
    },
    "group3": {
        "name": "t > 1200 ms",
        "count": 0,
        "percentage": 0
    },
    "group4": {
        "name": "failed",
        "count": 0,
        "percentage": 0
    },
    "meanNumberOfRequestsPerSecond": {
        "total": 0.014705882352941176,
        "ok": 0.014705882352941176,
        "ko": 0
    }
}
    },"req_eligible-contin-d7bc8": {
        "type": "REQUEST",
        "name": "Eligible Continue",
"path": "Eligible Continue",
"pathFormatted": "req_eligible-contin-d7bc8",
"stats": {
    "name": "Eligible Continue",
    "numberOfRequests": {
        "total": 1,
        "ok": 1,
        "ko": 0
    },
    "minResponseTime": {
        "total": 233,
        "ok": 233,
        "ko": 0
    },
    "maxResponseTime": {
        "total": 233,
        "ok": 233,
        "ko": 0
    },
    "meanResponseTime": {
        "total": 233,
        "ok": 233,
        "ko": 0
    },
    "standardDeviation": {
        "total": 0,
        "ok": 0,
        "ko": 0
    },
    "percentiles1": {
        "total": 233,
        "ok": 233,
        "ko": 0
    },
    "percentiles2": {
        "total": 233,
        "ok": 233,
        "ko": 0
    },
    "percentiles3": {
        "total": 233,
        "ok": 233,
        "ko": 0
    },
    "percentiles4": {
        "total": 233,
        "ok": 233,
        "ko": 0
    },
    "group1": {
        "name": "t < 800 ms",
        "count": 1,
        "percentage": 100
    },
    "group2": {
        "name": "800 ms < t < 1200 ms",
        "count": 0,
        "percentage": 0
    },
    "group3": {
        "name": "t > 1200 ms",
        "count": 0,
        "percentage": 0
    },
    "group4": {
        "name": "failed",
        "count": 0,
        "percentage": 0
    },
    "meanNumberOfRequestsPerSecond": {
        "total": 0.014705882352941176,
        "ok": 0.014705882352941176,
        "ko": 0
    }
}
    },"req_task-list---get-370bf": {
        "type": "REQUEST",
        "name": "Task list - GET",
"path": "Task list - GET",
"pathFormatted": "req_task-list---get-370bf",
"stats": {
    "name": "Task list - GET",
    "numberOfRequests": {
        "total": 1,
        "ok": 1,
        "ko": 0
    },
    "minResponseTime": {
        "total": 471,
        "ok": 471,
        "ko": 0
    },
    "maxResponseTime": {
        "total": 471,
        "ok": 471,
        "ko": 0
    },
    "meanResponseTime": {
        "total": 471,
        "ok": 471,
        "ko": 0
    },
    "standardDeviation": {
        "total": 0,
        "ok": 0,
        "ko": 0
    },
    "percentiles1": {
        "total": 471,
        "ok": 471,
        "ko": 0
    },
    "percentiles2": {
        "total": 471,
        "ok": 471,
        "ko": 0
    },
    "percentiles3": {
        "total": 471,
        "ok": 471,
        "ko": 0
    },
    "percentiles4": {
        "total": 471,
        "ok": 471,
        "ko": 0
    },
    "group1": {
        "name": "t < 800 ms",
        "count": 1,
        "percentage": 100
    },
    "group2": {
        "name": "800 ms < t < 1200 ms",
        "count": 0,
        "percentage": 0
    },
    "group3": {
        "name": "t > 1200 ms",
        "count": 0,
        "percentage": 0
    },
    "group4": {
        "name": "failed",
        "count": 0,
        "percentage": 0
    },
    "meanNumberOfRequestsPerSecond": {
        "total": 0.014705882352941176,
        "ok": 0.014705882352941176,
        "ko": 0
    }
}
    },"req_resolving-this--dbfd2": {
        "type": "REQUEST",
        "name": "Resolving this dispute - GET",
"path": "Resolving this dispute - GET",
"pathFormatted": "req_resolving-this--dbfd2",
"stats": {
    "name": "Resolving this dispute - GET",
    "numberOfRequests": {
        "total": 1,
        "ok": 1,
        "ko": 0
    },
    "minResponseTime": {
        "total": 325,
        "ok": 325,
        "ko": 0
    },
    "maxResponseTime": {
        "total": 325,
        "ok": 325,
        "ko": 0
    },
    "meanResponseTime": {
        "total": 325,
        "ok": 325,
        "ko": 0
    },
    "standardDeviation": {
        "total": 0,
        "ok": 0,
        "ko": 0
    },
    "percentiles1": {
        "total": 325,
        "ok": 325,
        "ko": 0
    },
    "percentiles2": {
        "total": 325,
        "ok": 325,
        "ko": 0
    },
    "percentiles3": {
        "total": 325,
        "ok": 325,
        "ko": 0
    },
    "percentiles4": {
        "total": 325,
        "ok": 325,
        "ko": 0
    },
    "group1": {
        "name": "t < 800 ms",
        "count": 1,
        "percentage": 100
    },
    "group2": {
        "name": "800 ms < t < 1200 ms",
        "count": 0,
        "percentage": 0
    },
    "group3": {
        "name": "t > 1200 ms",
        "count": 0,
        "percentage": 0
    },
    "group4": {
        "name": "failed",
        "count": 0,
        "percentage": 0
    },
    "meanNumberOfRequestsPerSecond": {
        "total": 0.014705882352941176,
        "ok": 0.014705882352941176,
        "ko": 0
    }
}
    },"req_resolving-this--358a3": {
        "type": "REQUEST",
        "name": "Resolving this dispute - POST",
"path": "Resolving this dispute - POST",
"pathFormatted": "req_resolving-this--358a3",
"stats": {
    "name": "Resolving this dispute - POST",
    "numberOfRequests": {
        "total": 1,
        "ok": 1,
        "ko": 0
    },
    "minResponseTime": {
        "total": 441,
        "ok": 441,
        "ko": 0
    },
    "maxResponseTime": {
        "total": 441,
        "ok": 441,
        "ko": 0
    },
    "meanResponseTime": {
        "total": 441,
        "ok": 441,
        "ko": 0
    },
    "standardDeviation": {
        "total": 0,
        "ok": 0,
        "ko": 0
    },
    "percentiles1": {
        "total": 441,
        "ok": 441,
        "ko": 0
    },
    "percentiles2": {
        "total": 441,
        "ok": 441,
        "ko": 0
    },
    "percentiles3": {
        "total": 441,
        "ok": 441,
        "ko": 0
    },
    "percentiles4": {
        "total": 441,
        "ok": 441,
        "ko": 0
    },
    "group1": {
        "name": "t < 800 ms",
        "count": 1,
        "percentage": 100
    },
    "group2": {
        "name": "800 ms < t < 1200 ms",
        "count": 0,
        "percentage": 0
    },
    "group3": {
        "name": "t > 1200 ms",
        "count": 0,
        "percentage": 0
    },
    "group4": {
        "name": "failed",
        "count": 0,
        "percentage": 0
    },
    "meanNumberOfRequestsPerSecond": {
        "total": 0.014705882352941176,
        "ok": 0.014705882352941176,
        "ko": 0
    }
}
    },"req_resolving-this--d1c9a": {
        "type": "REQUEST",
        "name": "Resolving this dispute - POST Redirect 1",
"path": "Resolving this dispute - POST Redirect 1",
"pathFormatted": "req_resolving-this--d1c9a",
"stats": {
    "name": "Resolving this dispute - POST Redirect 1",
    "numberOfRequests": {
        "total": 1,
        "ok": 1,
        "ko": 0
    },
    "minResponseTime": {
        "total": 307,
        "ok": 307,
        "ko": 0
    },
    "maxResponseTime": {
        "total": 307,
        "ok": 307,
        "ko": 0
    },
    "meanResponseTime": {
        "total": 307,
        "ok": 307,
        "ko": 0
    },
    "standardDeviation": {
        "total": 0,
        "ok": 0,
        "ko": 0
    },
    "percentiles1": {
        "total": 307,
        "ok": 307,
        "ko": 0
    },
    "percentiles2": {
        "total": 307,
        "ok": 307,
        "ko": 0
    },
    "percentiles3": {
        "total": 307,
        "ok": 307,
        "ko": 0
    },
    "percentiles4": {
        "total": 307,
        "ok": 307,
        "ko": 0
    },
    "group1": {
        "name": "t < 800 ms",
        "count": 1,
        "percentage": 100
    },
    "group2": {
        "name": "800 ms < t < 1200 ms",
        "count": 0,
        "percentage": 0
    },
    "group3": {
        "name": "t > 1200 ms",
        "count": 0,
        "percentage": 0
    },
    "group4": {
        "name": "failed",
        "count": 0,
        "percentage": 0
    },
    "meanNumberOfRequestsPerSecond": {
        "total": 0.014705882352941176,
        "ok": 0.014705882352941176,
        "ko": 0
    }
}
    },"req_completing-clai-26dee": {
        "type": "REQUEST",
        "name": "Completing claim - GET",
"path": "Completing claim - GET",
"pathFormatted": "req_completing-clai-26dee",
"stats": {
    "name": "Completing claim - GET",
    "numberOfRequests": {
        "total": 1,
        "ok": 1,
        "ko": 0
    },
    "minResponseTime": {
        "total": 252,
        "ok": 252,
        "ko": 0
    },
    "maxResponseTime": {
        "total": 252,
        "ok": 252,
        "ko": 0
    },
    "meanResponseTime": {
        "total": 252,
        "ok": 252,
        "ko": 0
    },
    "standardDeviation": {
        "total": 0,
        "ok": 0,
        "ko": 0
    },
    "percentiles1": {
        "total": 252,
        "ok": 252,
        "ko": 0
    },
    "percentiles2": {
        "total": 252,
        "ok": 252,
        "ko": 0
    },
    "percentiles3": {
        "total": 252,
        "ok": 252,
        "ko": 0
    },
    "percentiles4": {
        "total": 252,
        "ok": 252,
        "ko": 0
    },
    "group1": {
        "name": "t < 800 ms",
        "count": 1,
        "percentage": 100
    },
    "group2": {
        "name": "800 ms < t < 1200 ms",
        "count": 0,
        "percentage": 0
    },
    "group3": {
        "name": "t > 1200 ms",
        "count": 0,
        "percentage": 0
    },
    "group4": {
        "name": "failed",
        "count": 0,
        "percentage": 0
    },
    "meanNumberOfRequestsPerSecond": {
        "total": 0.014705882352941176,
        "ok": 0.014705882352941176,
        "ko": 0
    }
}
    },"req_completing-clai-ab354": {
        "type": "REQUEST",
        "name": "Completing claim - POST",
"path": "Completing claim - POST",
"pathFormatted": "req_completing-clai-ab354",
"stats": {
    "name": "Completing claim - POST",
    "numberOfRequests": {
        "total": 1,
        "ok": 1,
        "ko": 0
    },
    "minResponseTime": {
        "total": 458,
        "ok": 458,
        "ko": 0
    },
    "maxResponseTime": {
        "total": 458,
        "ok": 458,
        "ko": 0
    },
    "meanResponseTime": {
        "total": 458,
        "ok": 458,
        "ko": 0
    },
    "standardDeviation": {
        "total": 0,
        "ok": 0,
        "ko": 0
    },
    "percentiles1": {
        "total": 458,
        "ok": 458,
        "ko": 0
    },
    "percentiles2": {
        "total": 458,
        "ok": 458,
        "ko": 0
    },
    "percentiles3": {
        "total": 458,
        "ok": 458,
        "ko": 0
    },
    "percentiles4": {
        "total": 458,
        "ok": 458,
        "ko": 0
    },
    "group1": {
        "name": "t < 800 ms",
        "count": 1,
        "percentage": 100
    },
    "group2": {
        "name": "800 ms < t < 1200 ms",
        "count": 0,
        "percentage": 0
    },
    "group3": {
        "name": "t > 1200 ms",
        "count": 0,
        "percentage": 0
    },
    "group4": {
        "name": "failed",
        "count": 0,
        "percentage": 0
    },
    "meanNumberOfRequestsPerSecond": {
        "total": 0.014705882352941176,
        "ok": 0.014705882352941176,
        "ko": 0
    }
}
    },"req_completing-clai-3a805": {
        "type": "REQUEST",
        "name": "Completing claim - POST Redirect 1",
"path": "Completing claim - POST Redirect 1",
"pathFormatted": "req_completing-clai-3a805",
"stats": {
    "name": "Completing claim - POST Redirect 1",
    "numberOfRequests": {
        "total": 1,
        "ok": 1,
        "ko": 0
    },
    "minResponseTime": {
        "total": 304,
        "ok": 304,
        "ko": 0
    },
    "maxResponseTime": {
        "total": 304,
        "ok": 304,
        "ko": 0
    },
    "meanResponseTime": {
        "total": 304,
        "ok": 304,
        "ko": 0
    },
    "standardDeviation": {
        "total": 0,
        "ok": 0,
        "ko": 0
    },
    "percentiles1": {
        "total": 304,
        "ok": 304,
        "ko": 0
    },
    "percentiles2": {
        "total": 304,
        "ok": 304,
        "ko": 0
    },
    "percentiles3": {
        "total": 304,
        "ok": 304,
        "ko": 0
    },
    "percentiles4": {
        "total": 304,
        "ok": 304,
        "ko": 0
    },
    "group1": {
        "name": "t < 800 ms",
        "count": 1,
        "percentage": 100
    },
    "group2": {
        "name": "800 ms < t < 1200 ms",
        "count": 0,
        "percentage": 0
    },
    "group3": {
        "name": "t > 1200 ms",
        "count": 0,
        "percentage": 0
    },
    "group4": {
        "name": "failed",
        "count": 0,
        "percentage": 0
    },
    "meanNumberOfRequestsPerSecond": {
        "total": 0.014705882352941176,
        "ok": 0.014705882352941176,
        "ko": 0
    }
}
    },"req_party-type-sele-eb94b": {
        "type": "REQUEST",
        "name": "Party type selection - GET",
"path": "Party type selection - GET",
"pathFormatted": "req_party-type-sele-eb94b",
"stats": {
    "name": "Party type selection - GET",
    "numberOfRequests": {
        "total": 1,
        "ok": 1,
        "ko": 0
    },
    "minResponseTime": {
        "total": 351,
        "ok": 351,
        "ko": 0
    },
    "maxResponseTime": {
        "total": 351,
        "ok": 351,
        "ko": 0
    },
    "meanResponseTime": {
        "total": 351,
        "ok": 351,
        "ko": 0
    },
    "standardDeviation": {
        "total": 0,
        "ok": 0,
        "ko": 0
    },
    "percentiles1": {
        "total": 351,
        "ok": 351,
        "ko": 0
    },
    "percentiles2": {
        "total": 351,
        "ok": 351,
        "ko": 0
    },
    "percentiles3": {
        "total": 351,
        "ok": 351,
        "ko": 0
    },
    "percentiles4": {
        "total": 351,
        "ok": 351,
        "ko": 0
    },
    "group1": {
        "name": "t < 800 ms",
        "count": 1,
        "percentage": 100
    },
    "group2": {
        "name": "800 ms < t < 1200 ms",
        "count": 0,
        "percentage": 0
    },
    "group3": {
        "name": "t > 1200 ms",
        "count": 0,
        "percentage": 0
    },
    "group4": {
        "name": "failed",
        "count": 0,
        "percentage": 0
    },
    "meanNumberOfRequestsPerSecond": {
        "total": 0.014705882352941176,
        "ok": 0.014705882352941176,
        "ko": 0
    }
}
    },"req_party-type-sele-53c10": {
        "type": "REQUEST",
        "name": "Party type selection - POST",
"path": "Party type selection - POST",
"pathFormatted": "req_party-type-sele-53c10",
"stats": {
    "name": "Party type selection - POST",
    "numberOfRequests": {
        "total": 1,
        "ok": 1,
        "ko": 0
    },
    "minResponseTime": {
        "total": 354,
        "ok": 354,
        "ko": 0
    },
    "maxResponseTime": {
        "total": 354,
        "ok": 354,
        "ko": 0
    },
    "meanResponseTime": {
        "total": 354,
        "ok": 354,
        "ko": 0
    },
    "standardDeviation": {
        "total": 0,
        "ok": 0,
        "ko": 0
    },
    "percentiles1": {
        "total": 354,
        "ok": 354,
        "ko": 0
    },
    "percentiles2": {
        "total": 354,
        "ok": 354,
        "ko": 0
    },
    "percentiles3": {
        "total": 354,
        "ok": 354,
        "ko": 0
    },
    "percentiles4": {
        "total": 354,
        "ok": 354,
        "ko": 0
    },
    "group1": {
        "name": "t < 800 ms",
        "count": 1,
        "percentage": 100
    },
    "group2": {
        "name": "800 ms < t < 1200 ms",
        "count": 0,
        "percentage": 0
    },
    "group3": {
        "name": "t > 1200 ms",
        "count": 0,
        "percentage": 0
    },
    "group4": {
        "name": "failed",
        "count": 0,
        "percentage": 0
    },
    "meanNumberOfRequestsPerSecond": {
        "total": 0.014705882352941176,
        "ok": 0.014705882352941176,
        "ko": 0
    }
}
    },"req_party-type-sele-83715": {
        "type": "REQUEST",
        "name": "Party type selection - POST Redirect 1",
"path": "Party type selection - POST Redirect 1",
"pathFormatted": "req_party-type-sele-83715",
"stats": {
    "name": "Party type selection - POST Redirect 1",
    "numberOfRequests": {
        "total": 1,
        "ok": 1,
        "ko": 0
    },
    "minResponseTime": {
        "total": 309,
        "ok": 309,
        "ko": 0
    },
    "maxResponseTime": {
        "total": 309,
        "ok": 309,
        "ko": 0
    },
    "meanResponseTime": {
        "total": 309,
        "ok": 309,
        "ko": 0
    },
    "standardDeviation": {
        "total": 0,
        "ok": 0,
        "ko": 0
    },
    "percentiles1": {
        "total": 309,
        "ok": 309,
        "ko": 0
    },
    "percentiles2": {
        "total": 309,
        "ok": 309,
        "ko": 0
    },
    "percentiles3": {
        "total": 309,
        "ok": 309,
        "ko": 0
    },
    "percentiles4": {
        "total": 309,
        "ok": 309,
        "ko": 0
    },
    "group1": {
        "name": "t < 800 ms",
        "count": 1,
        "percentage": 100
    },
    "group2": {
        "name": "800 ms < t < 1200 ms",
        "count": 0,
        "percentage": 0
    },
    "group3": {
        "name": "t > 1200 ms",
        "count": 0,
        "percentage": 0
    },
    "group4": {
        "name": "failed",
        "count": 0,
        "percentage": 0
    },
    "meanNumberOfRequestsPerSecond": {
        "total": 0.014705882352941176,
        "ok": 0.014705882352941176,
        "ko": 0
    }
}
    },"req_your-details----55652": {
        "type": "REQUEST",
        "name": "Your details - POST",
"path": "Your details - POST",
"pathFormatted": "req_your-details----55652",
"stats": {
    "name": "Your details - POST",
    "numberOfRequests": {
        "total": 1,
        "ok": 1,
        "ko": 0
    },
    "minResponseTime": {
        "total": 679,
        "ok": 679,
        "ko": 0
    },
    "maxResponseTime": {
        "total": 679,
        "ok": 679,
        "ko": 0
    },
    "meanResponseTime": {
        "total": 679,
        "ok": 679,
        "ko": 0
    },
    "standardDeviation": {
        "total": 0,
        "ok": 0,
        "ko": 0
    },
    "percentiles1": {
        "total": 679,
        "ok": 679,
        "ko": 0
    },
    "percentiles2": {
        "total": 679,
        "ok": 679,
        "ko": 0
    },
    "percentiles3": {
        "total": 679,
        "ok": 679,
        "ko": 0
    },
    "percentiles4": {
        "total": 679,
        "ok": 679,
        "ko": 0
    },
    "group1": {
        "name": "t < 800 ms",
        "count": 1,
        "percentage": 100
    },
    "group2": {
        "name": "800 ms < t < 1200 ms",
        "count": 0,
        "percentage": 0
    },
    "group3": {
        "name": "t > 1200 ms",
        "count": 0,
        "percentage": 0
    },
    "group4": {
        "name": "failed",
        "count": 0,
        "percentage": 0
    },
    "meanNumberOfRequestsPerSecond": {
        "total": 0.014705882352941176,
        "ok": 0.014705882352941176,
        "ko": 0
    }
}
    },"req_your-details----9638c": {
        "type": "REQUEST",
        "name": "Your details - POST Redirect 1",
"path": "Your details - POST Redirect 1",
"pathFormatted": "req_your-details----9638c",
"stats": {
    "name": "Your details - POST Redirect 1",
    "numberOfRequests": {
        "total": 1,
        "ok": 1,
        "ko": 0
    },
    "minResponseTime": {
        "total": 305,
        "ok": 305,
        "ko": 0
    },
    "maxResponseTime": {
        "total": 305,
        "ok": 305,
        "ko": 0
    },
    "meanResponseTime": {
        "total": 305,
        "ok": 305,
        "ko": 0
    },
    "standardDeviation": {
        "total": 0,
        "ok": 0,
        "ko": 0
    },
    "percentiles1": {
        "total": 305,
        "ok": 305,
        "ko": 0
    },
    "percentiles2": {
        "total": 305,
        "ok": 305,
        "ko": 0
    },
    "percentiles3": {
        "total": 305,
        "ok": 305,
        "ko": 0
    },
    "percentiles4": {
        "total": 305,
        "ok": 305,
        "ko": 0
    },
    "group1": {
        "name": "t < 800 ms",
        "count": 1,
        "percentage": 100
    },
    "group2": {
        "name": "800 ms < t < 1200 ms",
        "count": 0,
        "percentage": 0
    },
    "group3": {
        "name": "t > 1200 ms",
        "count": 0,
        "percentage": 0
    },
    "group4": {
        "name": "failed",
        "count": 0,
        "percentage": 0
    },
    "meanNumberOfRequestsPerSecond": {
        "total": 0.014705882352941176,
        "ok": 0.014705882352941176,
        "ko": 0
    }
}
    },"req_date-of-birth---017f5": {
        "type": "REQUEST",
        "name": "Date of birth - POST",
"path": "Date of birth - POST",
"pathFormatted": "req_date-of-birth---017f5",
"stats": {
    "name": "Date of birth - POST",
    "numberOfRequests": {
        "total": 1,
        "ok": 1,
        "ko": 0
    },
    "minResponseTime": {
        "total": 461,
        "ok": 461,
        "ko": 0
    },
    "maxResponseTime": {
        "total": 461,
        "ok": 461,
        "ko": 0
    },
    "meanResponseTime": {
        "total": 461,
        "ok": 461,
        "ko": 0
    },
    "standardDeviation": {
        "total": 0,
        "ok": 0,
        "ko": 0
    },
    "percentiles1": {
        "total": 461,
        "ok": 461,
        "ko": 0
    },
    "percentiles2": {
        "total": 461,
        "ok": 461,
        "ko": 0
    },
    "percentiles3": {
        "total": 461,
        "ok": 461,
        "ko": 0
    },
    "percentiles4": {
        "total": 461,
        "ok": 461,
        "ko": 0
    },
    "group1": {
        "name": "t < 800 ms",
        "count": 1,
        "percentage": 100
    },
    "group2": {
        "name": "800 ms < t < 1200 ms",
        "count": 0,
        "percentage": 0
    },
    "group3": {
        "name": "t > 1200 ms",
        "count": 0,
        "percentage": 0
    },
    "group4": {
        "name": "failed",
        "count": 0,
        "percentage": 0
    },
    "meanNumberOfRequestsPerSecond": {
        "total": 0.014705882352941176,
        "ok": 0.014705882352941176,
        "ko": 0
    }
}
    },"req_date-of-birth---6bbc9": {
        "type": "REQUEST",
        "name": "Date of birth - POST Redirect 1",
"path": "Date of birth - POST Redirect 1",
"pathFormatted": "req_date-of-birth---6bbc9",
"stats": {
    "name": "Date of birth - POST Redirect 1",
    "numberOfRequests": {
        "total": 1,
        "ok": 1,
        "ko": 0
    },
    "minResponseTime": {
        "total": 307,
        "ok": 307,
        "ko": 0
    },
    "maxResponseTime": {
        "total": 307,
        "ok": 307,
        "ko": 0
    },
    "meanResponseTime": {
        "total": 307,
        "ok": 307,
        "ko": 0
    },
    "standardDeviation": {
        "total": 0,
        "ok": 0,
        "ko": 0
    },
    "percentiles1": {
        "total": 307,
        "ok": 307,
        "ko": 0
    },
    "percentiles2": {
        "total": 307,
        "ok": 307,
        "ko": 0
    },
    "percentiles3": {
        "total": 307,
        "ok": 307,
        "ko": 0
    },
    "percentiles4": {
        "total": 307,
        "ok": 307,
        "ko": 0
    },
    "group1": {
        "name": "t < 800 ms",
        "count": 1,
        "percentage": 100
    },
    "group2": {
        "name": "800 ms < t < 1200 ms",
        "count": 0,
        "percentage": 0
    },
    "group3": {
        "name": "t > 1200 ms",
        "count": 0,
        "percentage": 0
    },
    "group4": {
        "name": "failed",
        "count": 0,
        "percentage": 0
    },
    "meanNumberOfRequestsPerSecond": {
        "total": 0.014705882352941176,
        "ok": 0.014705882352941176,
        "ko": 0
    }
}
    },"req_mobile-number---efca8": {
        "type": "REQUEST",
        "name": "Mobile number - POST",
"path": "Mobile number - POST",
"pathFormatted": "req_mobile-number---efca8",
"stats": {
    "name": "Mobile number - POST",
    "numberOfRequests": {
        "total": 1,
        "ok": 1,
        "ko": 0
    },
    "minResponseTime": {
        "total": 560,
        "ok": 560,
        "ko": 0
    },
    "maxResponseTime": {
        "total": 560,
        "ok": 560,
        "ko": 0
    },
    "meanResponseTime": {
        "total": 560,
        "ok": 560,
        "ko": 0
    },
    "standardDeviation": {
        "total": 0,
        "ok": 0,
        "ko": 0
    },
    "percentiles1": {
        "total": 560,
        "ok": 560,
        "ko": 0
    },
    "percentiles2": {
        "total": 560,
        "ok": 560,
        "ko": 0
    },
    "percentiles3": {
        "total": 560,
        "ok": 560,
        "ko": 0
    },
    "percentiles4": {
        "total": 560,
        "ok": 560,
        "ko": 0
    },
    "group1": {
        "name": "t < 800 ms",
        "count": 1,
        "percentage": 100
    },
    "group2": {
        "name": "800 ms < t < 1200 ms",
        "count": 0,
        "percentage": 0
    },
    "group3": {
        "name": "t > 1200 ms",
        "count": 0,
        "percentage": 0
    },
    "group4": {
        "name": "failed",
        "count": 0,
        "percentage": 0
    },
    "meanNumberOfRequestsPerSecond": {
        "total": 0.014705882352941176,
        "ok": 0.014705882352941176,
        "ko": 0
    }
}
    },"req_mobile-number---b969a": {
        "type": "REQUEST",
        "name": "Mobile number - POST Redirect 1",
"path": "Mobile number - POST Redirect 1",
"pathFormatted": "req_mobile-number---b969a",
"stats": {
    "name": "Mobile number - POST Redirect 1",
    "numberOfRequests": {
        "total": 1,
        "ok": 1,
        "ko": 0
    },
    "minResponseTime": {
        "total": 307,
        "ok": 307,
        "ko": 0
    },
    "maxResponseTime": {
        "total": 307,
        "ok": 307,
        "ko": 0
    },
    "meanResponseTime": {
        "total": 307,
        "ok": 307,
        "ko": 0
    },
    "standardDeviation": {
        "total": 0,
        "ok": 0,
        "ko": 0
    },
    "percentiles1": {
        "total": 307,
        "ok": 307,
        "ko": 0
    },
    "percentiles2": {
        "total": 307,
        "ok": 307,
        "ko": 0
    },
    "percentiles3": {
        "total": 307,
        "ok": 307,
        "ko": 0
    },
    "percentiles4": {
        "total": 307,
        "ok": 307,
        "ko": 0
    },
    "group1": {
        "name": "t < 800 ms",
        "count": 1,
        "percentage": 100
    },
    "group2": {
        "name": "800 ms < t < 1200 ms",
        "count": 0,
        "percentage": 0
    },
    "group3": {
        "name": "t > 1200 ms",
        "count": 0,
        "percentage": 0
    },
    "group4": {
        "name": "failed",
        "count": 0,
        "percentage": 0
    },
    "meanNumberOfRequestsPerSecond": {
        "total": 0.014705882352941176,
        "ok": 0.014705882352941176,
        "ko": 0
    }
}
    }
}

}